README.rst
setup.py
torndsession/__init__.py
torndsession/compat.py
torndsession/driver.py
torndsession/filesession.py
torndsession/memcachedsession.py
torndsession/memorysession.py
torndsession/redissession.py
torndsession/session.py
torndsession/sessionhandler.py
torndsession.egg-info/PKG-INFO
torndsession.egg-info/SOURCES.txt
torndsession.egg-info/dependency_links.txt
torndsession.egg-info/requires.txt
torndsession.egg-info/top_level.txt
torndsession.egg-info/zip-safe