Metadata-Version: 1.1
Name: torndsession
Version: 1.1.5.1
Summary: Session extensions for Tornado
Home-page: http://github.com/mitchellchu/torndsession
Author: MitchellChu
Author-email: zxdjsj@126.com
License: MIT
Keywords: torndsession tornado session redis memcached memory file python
Platform: UNKNOWN
Classifier: License :: OSI Approved :: MIT License
Classifier: Topic :: Internet :: WWW/HTTP :: Session
Classifier: Programming Language :: Python :: 2.7
Classifier: Programming Language :: Python :: 3
Classifier: Environment :: Web Environment
Classifier: Intended Audience :: Developers
Classifier: Operating System :: OS Independent
